example/__init__.py
example/main.py
example/maze_generator.py
maze_runner/__init__.py
maze_runner/animation.py
maze_runner/maze.py
maze_runner/maze_creator.py
maze_runner/position.py
maze_runner/tests/__init__.py
maze_runner/tests/test_validate_sample_maps.py
maze_runner-0.3.4.dist-info/LICENSE
maze_runner-0.3.4.dist-info/METADATA
maze_runner-0.3.4.dist-info/WHEEL
maze_runner-0.3.4.dist-info/top_level.txt
maze_runner-0.3.4.dist-info/RECORD
