Metadata-Version: 2.1
Name: maze_runner
Version: 0.3.4
Summary: Programming challenge for CS students.
Home-page: https://github.com/matheusjardimb/maze_runner/
Download-URL: https://github.com/matheusjardimb/maze_runner/zipball/main
Author: Matheus Jardim Bernardes
Author-email: matheusjardimb@gmail.com
Maintainer: Matheus Jardim Bernardes
Maintainer-email: matheusjardimb@gmail.com
License: MIT License
License-File: LICENSE
